{"format_version":"0.2","provider_schemas":{"registry.terraform.io/ackama/statuscake":{"provider":{"version":0,"block":{"attributes":{"api_key":{"type":"string","description_kind":"plain","optional":true,"sensitive":true}},"description_kind":"plain"}},"resource_schemas":{"statuscake_contact_group":{"version":0,"block":{"attributes":{"email_addresses":{"type":["list","string"],"description":"List of email addresses","description_kind":"plain","optional":true},"id":{"type":"string","description_kind":"plain","optional":true,"computed":true},"integrations":{"type":["list","string"],"description":"List of integration IDs","description_kind":"plain","optional":true},"mobile_numbers":{"type":["list","string"],"description":"List of international format mobile phone numbers","description_kind":"plain","optional":true},"name":{"type":"string","description":"Name of the contact group","description_kind":"plain","required":true},"ping_url":{"type":"string","description":"URL or IP address of an endpoint to push uptime events. Currently this only supports HTTP GET endpoints","description_kind":"plain","optional":true}},"description":"Manages a StatusCake Contact Group","description_kind":"plain"}},"statuscake_uptime_test":{"version":0,"block":{"attributes":{"basic_pass":{"type":"string","description":"Basic authentication password","description_kind":"plain","optional":true,"sensitive":true},"basic_user":{"type":"string","description":"Basic authentication username","description_kind":"plain","optional":true},"check_rate":{"type":"number","description":"Number of seconds between tests","description_kind":"plain","required":true},"confirmation":{"type":"number","description":"Number of confirmation servers to confirm downtime before an alert is triggered","description_kind":"plain","optional":true},"contact_groups":{"type":["list","string"],"description":"List of contact group IDs","description_kind":"plain","optional":true},"cookie_storage":{"type":"bool","description":"Enable cookie storage","description_kind":"plain","optional":true},"custom_header":{"type":"string","description":"JSON object. Represents headers to be sent when making requests","description_kind":"plain","optional":true},"dns_ip_csv":{"type":"string","description":"Comma separated list of IP addresses to compare against returned DNS records","description_kind":"plain","optional":true},"dns_server":{"type":"string","description":"Hostname or IP address of the nameserver to query","description_kind":"plain","optional":true},"do_not_find":{"type":"bool","description":"Whether to consider the test as down if the string in FindString is present within the response","description_kind":"plain","optional":true},"enable_ssl_alert":{"type":"bool","description":"Send an alert if the SSL certificate is soon to expire","description_kind":"plain","optional":true},"final_endpoint":{"type":"string","description":"Specify where the redirect chain should end","description_kind":"plain","optional":true},"find_string":{"type":"string","description":"String to look for within the response. Considered down if not found","description_kind":"plain","optional":true},"follow_redirects":{"type":"bool","description":"Allow tests to follow redirects","description_kind":"plain","optional":true},"host":{"type":"string","description":"Name of the hosting provider","description_kind":"plain","optional":true},"id":{"type":"string","description_kind":"plain","optional":true,"computed":true},"include_header":{"type":"bool","description":"Include header content in string match search","description_kind":"plain","optional":true},"name":{"type":"string","description":"Name of the test","description_kind":"plain","required":true},"paused":{"type":"bool","description":"Whether the test should be run","description_kind":"plain","optional":true},"port":{"type":"number","description":"Destination port for TCP tests","description_kind":"plain","optional":true},"post_body":{"type":"string","description":"JSON object. This is converted to form data on request","description_kind":"plain","optional":true},"post_raw":{"type":"string","description":"Raw HTTP POST string to send to the server","description_kind":"plain","optional":true},"regions":{"type":["list","string"],"description":"List of regions on which to run tests. The values required for this parameter can be retrieved from the GET /v1/uptime-locations endpoint.","description_kind":"plain","optional":true},"status_codes":{"type":["list","string"],"description":"List of status codes that trigger an alert","description_kind":"plain","optional":true},"tags":{"type":["list","string"],"description":"List of tags","description_kind":"plain","optional":true},"test_type":{"type":"string","description":"Uptime test type","description_kind":"plain","required":true},"timeout":{"type":"number","description":"How long to wait to receive the first byte","description_kind":"plain","optional":true},"trigger_rate":{"type":"number","description":"The number of minutes to wait before sending an alert","description_kind":"plain","optional":true},"user_agent":{"type":"string","description":"User agent to be used when making requests","description_kind":"plain","optional":true},"website_url":{"type":"string","description":"URL or IP address of the website under test","description_kind":"plain","required":true}},"description":"Manages a StatusCake Uptime Test","description_kind":"plain"}}}}}}
