{"format_version":"0.2","provider_schemas":{"registry.terraform.io/elastic-infra/ldap":{"provider":{"version":0,"block":{"attributes":{"bind_password":{"type":"string","description":"Password to authenticate the Bind user.","description_kind":"plain","required":true},"bind_user":{"type":"string","description":"Bind user to be used for authenticating on the LDAP server.","description_kind":"plain","required":true},"ldap_host":{"type":"string","description":"The LDAP server to connect to.","description_kind":"plain","required":true},"ldap_port":{"type":"number","description":"The LDAP protocol port (default: 389).","description_kind":"plain","optional":true},"start_tls":{"type":"bool","description":"Upgrade TLS to secure the connection (default: false).","description_kind":"plain","optional":true},"tls":{"type":"bool","description":"Enable TLS encryption for LDAP (LDAPS) (default: false).","description_kind":"plain","optional":true},"tls_insecure":{"type":"bool","description":"Don't verify server TLS certificate (default: false).","description_kind":"plain","optional":true}},"description_kind":"plain"}},"resource_schemas":{"ldap_object":{"version":0,"block":{"attributes":{"attributes":{"type":["set",["map","string"]],"description":"The map of attributes of this object; each attribute can be multi-valued.","description_kind":"plain","optional":true},"dn":{"type":"string","description":"The Distinguished Name (DN) of the object, as the concatenation of its RDN (unique among siblings) and its parent's DN.","description_kind":"plain","required":true},"id":{"type":"string","description_kind":"plain","optional":true,"computed":true},"object_classes":{"type":["set","string"],"description":"The set of classes this object conforms to (e.g. organizationalUnit, inetOrgPerson).","description_kind":"plain","required":true}},"description":"Provides a LDAP Object.","description_kind":"plain"}}}}}}
