{"format_version":"0.2","provider_schemas":{"registry.terraform.io/hierynomus/jumphost":{"provider":{"version":0,"block":{"attributes":{"hostname":{"type":"string","description_kind":"plain","optional":true},"key":{"type":"string","description_kind":"plain","optional":true,"sensitive":true},"password":{"type":"string","description_kind":"plain","optional":true,"sensitive":true},"port":{"type":"number","description_kind":"plain","optional":true},"use_agent":{"type":"bool","description_kind":"plain","optional":true},"username":{"type":"string","description_kind":"plain","optional":true}},"description_kind":"plain"}},"data_source_schemas":{"jumphost_ssh":{"version":0,"block":{"attributes":{"hostname":{"type":"string","description_kind":"plain","required":true},"id":{"type":"number","description_kind":"plain","computed":true},"local_port":{"type":"number","description_kind":"plain","computed":true},"port":{"type":"number","description_kind":"plain","required":true}},"description_kind":"plain"}}}}}}
